{"cookies": [{"name": "pac1", "value": "r41ng1h4", "domain": "live.centrosportivoitaliano.it", "path": "/", "expires": 1789919163.093723, "httpOnly": false, "secure": false, "sameSite": "Lax"}, {"name": "pac2", "value": "042", "domain": "live.centrosportivoitaliano.it", "path": "/", "expires": 1789910084.4485, "httpOnly": false, "secure": false, "sameSite": "Lax"}, {"name": "pac3", "value": "CA7", "domain": "live.centrosportivoitaliano.it", "path": "/", "expires": 1789910084.448519, "httpOnly": false, "secure": false, "sameSite": "Lax"}, {"name": "ASPSESSIONIDSCTBBQSA", "value": "EKALFOICFOIOAHNODDNOAJCN", "domain": "live.centrosportivoitaliano.it", "path": "/", "expires": -1, "httpOnly": false, "secure": false, "sameSite": "Lax"}, {"name": "ASPSESSIONIDQASBDQTB", "value": "FBMBEKFDHDOHMBEMIMANPGCH", "domain": "live.centrosportivoitaliano.it", "path": "/", "expires": -1, "httpOnly": false, "secure": false, "sameSite": "Lax"}, {"name": "cf_clearance", "value": "wVBwAPKRnQWGO.xNzVgWoex.dCtJoRpPOamWilez3Lo-1758383161-1.2.1.1-Liq2_2r8YPwLYGeLyehCGvX9mQhIxiXfWy.fzJN9CeEP4zdMkl6lydK9lFXTW07Mk5IqcNe55Tr3B0secfsZirFKcqIGSFIzpR4wIypIvhxQlEke2xpWf5amEhIv0FLngPEboJyT1Z9p3IDNXsv7moaDpX1PZJAcSQiK7vbnrUGZ8bBJ.7YiZQWFGsZRVIA.LOnLsAIWp1kWytAkonwtZcxqGie6jcWVUMuZIuLbHqU", "domain": ".centrosportivoitaliano.it", "path": "/", "expires": 1789919161.728756, "httpOnly": true, "secure": true, "sameSite": "None", "partitionKey": "https://centrosportivoitaliano.it", "_crHasCrossSiteAncestor": false}], "origins": []}